pydantic_br_validator/__init__.py
pydantic_br_validator/field_class_errors.py
pydantic_br_validator/field_erros.py
pydantic_br_validator/get_versions.py
pydantic_br_validator/fields/base_field.py
pydantic_br_validator/fields/base_field_v2.py
pydantic_br_validator/fields/cep_field.py
pydantic_br_validator/fields/cnh_field.py
pydantic_br_validator/fields/cnpj_field.py
pydantic_br_validator/fields/cpf_field.py
pydantic_br_validator/fields/rg_field.py
pydantic_br_validator/validators/base_validator.py
pydantic_br_validator/validators/cep_validator.py
pydantic_br_validator/validators/cnh_validator.py
pydantic_br_validator/validators/cnpj_validator.py
pydantic_br_validator/validators/cpf_validator.py
pydantic_br_validator/validators/rg_validator.py
pydantic_br_validator-0.8.1.dist-info/METADATA
pydantic_br_validator-0.8.1.dist-info/WHEEL
pydantic_br_validator-0.8.1.dist-info/top_level.txt
pydantic_br_validator-0.8.1.dist-info/RECORD
