Metadata-Version: 2.4
Name: pydantic-br-validator
Version: 0.8.1
Summary: Uma biblioteca python com modelos de validação para os principais documentos brasileiros
Requires-Python: >=3.9
Requires-Dist: pre-commit>=3.7.0
Requires-Dist: pydantic==2.10.5
